[
  {
    "_id": "smsbackuprestore",
    "_type": "dashboard",
    "_source": {
      "title": "smsbackuprestore",
      "hits": 0,
      "description": "",
      "panelsJSON": "[{\"col\":1,\"id\":\"Unique-By-Date\",\"panelIndex\":1,\"row\":1,\"size_x\":12,\"size_y\":2,\"type\":\"visualization\"},{\"col\":1,\"id\":\"Unique-Messages\",\"panelIndex\":2,\"row\":6,\"size_x\":4,\"size_y\":1,\"type\":\"visualization\"},{\"col\":8,\"id\":\"07e858a0-ed46-11e6-8d97-9d607c296e53\",\"panelIndex\":3,\"row\":3,\"size_x\":5,\"size_y\":5,\"type\":\"visualization\"},{\"col\":1,\"id\":\"62f97fe0-ed4a-11e6-896f-03591b103f36\",\"panelIndex\":4,\"row\":7,\"size_x\":4,\"size_y\":1,\"type\":\"visualization\"},{\"col\":5,\"id\":\"2163d640-eed3-11e6-bfa9-758d8493d5d5\",\"panelIndex\":5,\"row\":3,\"size_x\":3,\"size_y\":5,\"type\":\"visualization\"},{\"col\":1,\"id\":\"e3d8ea20-eed4-11e6-bfa9-758d8493d5d5\",\"panelIndex\":6,\"row\":8,\"size_x\":12,\"size_y\":5,\"type\":\"visualization\"},{\"col\":1,\"id\":\"49d43750-eed8-11e6-b82c-cfadc977342c\",\"panelIndex\":7,\"row\":3,\"size_x\":4,\"size_y\":3,\"type\":\"visualization\"},{\"col\":1,\"id\":\"77772060-ef40-11e6-a812-ddb6af4d8fac\",\"panelIndex\":8,\"row\":13,\"size_x\":12,\"size_y\":3,\"type\":\"visualization\"}]",
      "optionsJSON": "{\"darkTheme\":false}",
      "uiStateJSON": "{\"P-1\":{\"vis\":{\"legendOpen\":false}},\"P-2\":{\"spy\":{\"mode\":{\"fill\":false,\"name\":null}}},\"P-3\":{\"vis\":{\"params\":{\"sort\":{\"columnIndex\":1,\"direction\":\"desc\"}}}},\"P-5\":{\"vis\":{\"params\":{\"sort\":{\"columnIndex\":1,\"direction\":\"desc\"}}}},\"P-6\":{\"vis\":{\"params\":{\"sort\":{\"columnIndex\":3,\"direction\":\"desc\"}}}},\"P-7\":{\"spy\":{\"mode\":{\"fill\":false,\"name\":null}},\"vis\":{\"params\":{\"sort\":{\"columnIndex\":null,\"direction\":null}}}},\"P-8\":{\"vis\":{\"defaultColors\":{\"0% - 10%\":\"rgb(247,251,255)\",\"10% - 20%\":\"rgb(227,238,249)\",\"20% - 30%\":\"rgb(208,225,242)\",\"30% - 40%\":\"rgb(182,212,233)\",\"40% - 50%\":\"rgb(148,196,223)\",\"50% - 60%\":\"rgb(107,174,214)\",\"60% - 70%\":\"rgb(74,152,201)\",\"70% - 80%\":\"rgb(46,126,188)\",\"80% - 90%\":\"rgb(23,100,171)\",\"90% - 100%\":\"rgb(8,74,145)\"}}}}",
      "version": 1,
      "timeRestore": true,
      "timeTo": "now",
      "timeFrom": "now-5y",
      "refreshInterval": {
        "display": "Off",
        "pause": false,
        "value": 0
      },
      "kibanaSavedObjectMeta": {
        "searchSourceJSON": "{\"filter\":[{\"query\":{\"query_string\":{\"analyze_wildcard\":true,\"query\":\"*\"}}}]}"
      }
    }
  }
]